MANIFEST.in
README.md
requirements.txt
setup.py
adsutils/Unicode.py
adsutils/__init__.py
adsutils/ads_utils.py
adsutils/config.py
adsutils/errors.py
adsutils/newtrigdict.py
adsutils/sourcematchers.py
adsutils/utils.py
adsutils.egg-info/PKG-INFO
adsutils.egg-info/SOURCES.txt
adsutils.egg-info/dependency_links.txt
adsutils.egg-info/requires.txt
adsutils.egg-info/top_level.txt
adsutils/data/aps_abbrev.dat
adsutils/data/bibstems.dat
adsutils/data/conferences.dat
adsutils/data/conferences_abbrev.dat
adsutils/data/iop_elec.dat
adsutils/data/journals.dat
adsutils/data/journals_abbrev.dat
adsutils/data/needs_issue.dat
adsutils/data/notinADS.dat
adsutils/data/preprints.dat
adsutils/data/unicode.dat
adsutils/test/__init__.py
adsutils/test/nosetests.py
adsutils/test/test_bibcode.py
adsutils/test/test_resolver.py
adsutils/test/test_source_matcher.py