Metadata-Version: 1.1
Name: adsutils
Version: 1.0.33
Summary: A Python tool with some general ADS utilities
Home-page: http://github.com/adsabs/adsutils
Author: Edwin Henneken
Author-email: ehenneken@cfa.harvard.edu
License: MIT
Platform: UNKNOWN
Classifier: Development Status :: 4 - Beta
Classifier: Intended Audience :: Developers
Classifier: Programming Language :: Python
Classifier: Operating System :: POSIX :: Linux
Classifier: Topic :: Scientific/Engineering :: Astronomy
Classifier: Topic :: Internet :: WWW/HTTP :: Indexing/Search
Classifier: Topic :: Software Development :: Libraries :: Python Modules
Classifier: Topic :: Software Development :: Libraries
